IOL/__init__.py
iol_api_client-0.0.1.dist-info/LICENSE
iol_api_client-0.0.1.dist-info/METADATA
iol_api_client-0.0.1.dist-info/WHEEL
iol_api_client-0.0.1.dist-info/top_level.txt
iol_api_client-0.0.1.dist-info/RECORD
